Metadata-Version: 2.1
Name: pwnsandbox
Version: 0.31
Summary: Yet another pwn sandbox in CTF!
Home-page: https://github.com/unamer/PwnSandboxForCTF
Author: unamer
Author-email: n0nick@protonmail.com
License: GPLv3
Keywords: pwn sandbox ctf
Platform: UNKNOWN
Classifier: License :: OSI Approved :: GNU General Public License v3 (GPLv3)
Classifier: Programming Language :: Python :: 2.7
